MANIFEST.in
setup.cfg
setup.py
paPyro.egg-info/PKG-INFO
paPyro.egg-info/SOURCES.txt
paPyro.egg-info/dependency_links.txt
paPyro.egg-info/requires.txt
paPyro.egg-info/top_level.txt
papyro/__init__.py
papyro/designer.py
papyro/reportBase.py
papyro/reportPdf.py
papyro/reportPlainText.py
papyro/reports.py
papyro/ttfonts/__init__.py
papyro/ttfonts/arial.ttf
papyro/ttfonts/couriernew.ttf
papyro/ttfonts/georgia.ttf
papyro/ttfonts/lsans.ttf
papyro/ttfonts/msanserif.ttf
papyro/ttfonts/tahoma.ttf
papyro/ttfonts/times.ttf
papyro/ttfonts/vera.ttf
papyro/ttfonts/verdana.ttf