Metadata-Version: 1.0
Name: paPyro
Version: 1.0.3
Summary: A PDF report generator written in Python
Home-page: http://www.ender.es
Author: León Domingo
Author-email: leon.domingo@ender.es
License: UNKNOWN
Keywords: pdf reports ender
Platform: UNKNOWN
Classifier: Development Status :: 5 - Production/Stable
Classifier: Topic :: Utilities
